formpy/__init__.py
formpy/answer.py
formpy/form.py
formpy/question.py
formpy/template.py
formpy/utils/__init__.py
formpy/utils/img_processing.py
formpy/utils/template_definition.py
formpy_omr-0.1.3.dist-info/WHEEL
formpy_omr-0.1.3.dist-info/METADATA
formpy_omr-0.1.3.dist-info/RECORD
