Metadata-Version: 2.1
Name: formpy-omr
Version: 0.1.3
Summary: 
Author: Ismail Mohammed
Author-email: ismailmo4@gmail.com
Requires-Python: >=3.8,<4.0
Classifier: Programming Language :: Python :: 3
Classifier: Programming Language :: Python :: 3.8
Requires-Dist: click (>=8.0.2)
Requires-Dist: numpy (>=1.22.3,<2.0.0)
Requires-Dist: opencv-contrib-python (>=4.5.5,<5.0.0)
